Topsis_Dhruv_102103331/Topsis.py
Topsis_Dhruv_102103331/__init__.py
Topsis_Dhruv_102103331/cli.py
Topsis_Dhruv_102103331-0.1.0.dist-info/METADATA
Topsis_Dhruv_102103331-0.1.0.dist-info/WHEEL
Topsis_Dhruv_102103331-0.1.0.dist-info/entry_points.txt
Topsis_Dhruv_102103331-0.1.0.dist-info/top_level.txt
Topsis_Dhruv_102103331-0.1.0.dist-info/RECORD
