Metadata-Version: 2.1
Name: Topsis-Dhruv-102103331
Version: 0.1.0
Requires-Dist: numpy
Requires-Dist: pandas
